Workbook

Sheet Dashboard
A1: CRESTWOOD UNIVERSITY CAMPUS STORE
A2: Sales & Inventory Performance Dashboard | Spring Semester 2026
B5: TOTAL REVENUE | E5: UNITS SOLD | H5: AVG ORDER VALUE | K5: ITEMS TO REORDER
B6: =SUM('Sales Log'!H5:H111) -> 39675.92 | E6: =SUM('Sales Log'!F5:F111) -> 1041 | H6: =B6/E6 -> 38.113276 | K6: =Inventory!B27 -> 7
B7: Spring semester to date | E7: Across all categories | H7: Per transaction | K7: Below reorder threshold
B10: REVENUE BY CATEGORY | G10: MONTHLY REVENUE TREND | K10: STOCK STATUS
B11: Category | C11: Revenue | D11: % of Total | G11: Month | H11: Revenue | I11: Transactions | K11: Status | L11: Count | P11: _ProductID | Q11: _Revenue
B12: Textbooks | C12: =SUMIF('Sales Log'!$E$5:$E$111,B12,'Sales Log'!$H$5:$H$111) -> 17530.49 | D12: =C12/$B$6 -> 0.44184205 | G12: Jan | H12: =SUMIF('Sales Log'!$B$5:$B$111,G12,'Sales Log'!$H$5:$H$111) -> 7725.1 | I12: =COUNTIF('Sales Log'!$B$5:$B$111,G12) -> 20 | K12: OK | L12: =COUNTIF(Inventory!$H$5:$H$22,"OK") -> 11 | P12: CS-2001 | Q12: =SUMIF('Sales Log'!$C$5:$C$111,P12,'Sales Log'!$H$5:$H$111) -> 4589.49
B13: Apparel & Spirit Wear | C13: =SUMIF('Sales Log'!$E$5:$E$111,B13,'Sales Log'!$H$5:$H$111) -> 3793.39 | D13: =C13/$B$6 -> 0.095609377 | G13: Feb | H13: =SUMIF('Sales Log'!$B$5:$B$111,G13,'Sales Log'!$H$5:$H$111) -> 8842.07 | I13: =COUNTIF('Sales Log'!$B$5:$B$111,G13) -> 18 | K13: REORDER | L13: =COUNTIF(Inventory!$H$5:$H$22,"REORDER") -> 7 | P13: CS-2002 | Q13: =SUMIF('Sales Log'!$C$5:$C$111,P13,'Sales Log'!$H$5:$H$111) -> 3725
B14: Electronics & Supplies | C14: =SUMIF('Sales Log'!$E$5:$E$111,B14,'Sales Log'!$H$5:$H$111) -> 3164.41 | D14: =C14/$B$6 -> 0.079756437 | G14: Mar | H14: =SUMIF('Sales Log'!$B$5:$B$111,G14,'Sales Log'!$H$5:$H$111) -> 5689.62 | I14: =COUNTIF('Sales Log'!$B$5:$B$111,G14) -> 17 | P14: CS-2003 | Q14: =SUMIF('Sales Log'!$C$5:$C$111,P14,'Sales Log'!$H$5:$H$111) -> 9216
B15: Dining & Snacks | C15: =SUMIF('Sales Log'!$E$5:$E$111,B15,'Sales Log'!$H$5:$H$111) -> 1077.34 | D15: =C15/$B$6 -> 0.027153498 | G15: Apr | H15: =SUMIF('Sales Log'!$B$5:$B$111,G15,'Sales Log'!$H$5:$H$111) -> 7296.11 | I15: =COUNTIF('Sales Log'!$B$5:$B$111,G15) -> 19 | P15: CS-2004 | Q15: =SUMIF('Sales Log'!$C$5:$C$111,P15,'Sales Log'!$H$5:$H$111) -> 1034.77
B16: Dorm Essentials | C16: =SUMIF('Sales Log'!$E$5:$E$111,B16,'Sales Log'!$H$5:$H$111) -> 12697.2 | D16: =C16/$B$6 -> 0.32002282 | G16: May | H16: =SUMIF('Sales Log'!$B$5:$B$111,G16,'Sales Log'!$H$5:$H$111) -> 7934.75 | I16: =COUNTIF('Sales Log'!$B$5:$B$111,G16) -> 17 | P16: CS-2005 | Q16: =SUMIF('Sales Log'!$C$5:$C$111,P16,'Sales Log'!$H$5:$H$111) -> 2758.62
B17: School Supplies | C17: =SUMIF('Sales Log'!$E$5:$E$111,B17,'Sales Log'!$H$5:$H$111) -> 1413.09 | D17: =C17/$B$6 -> 0.035615809 | G17: Jun | H17: =SUMIF('Sales Log'!$B$5:$B$111,G17,'Sales Log'!$H$5:$H$111) -> 2188.27 | I17: =COUNTIF('Sales Log'!$B$5:$B$111,G17) -> 16 | P17: CS-2006 | Q17: =SUMIF('Sales Log'!$C$5:$C$111,P17,'Sales Log'!$H$5:$H$111) -> 0
P18: CS-2007 | Q18: =SUMIF('Sales Log'!$C$5:$C$111,P18,'Sales Log'!$H$5:$H$111) -> 1374.45
P19: CS-2008 | Q19: =SUMIF('Sales Log'!$C$5:$C$111,P19,'Sales Log'!$H$5:$H$111) -> 569.62
B20: TOP 5 PRODUCTS BY REVENUE | P20: CS-2009 | Q20: =SUMIF('Sales Log'!$C$5:$C$111,P20,'Sales Log'!$H$5:$H$111) -> 1220.34
B21: Rank | C21: Product Name | D21: Category | E21: Units Sold | F21: Revenue | P21: CS-2010 | Q21: =SUMIF('Sales Log'!$C$5:$C$111,P21,'Sales Log'!$H$5:$H$111) -> 751.06
B22: 1 | C22: =VLOOKUP(INDEX($P$12:$P$29,MATCH(F22,$Q$12:$Q$29,0)),Inventory!$A$5:$D$22,2,FALSE()) -> Mini Fridge | D22: =VLOOKUP(INDEX($P$12:$P$29,MATCH(F22,$Q$12:$Q$29,0)),Inventory!$A$5:$D$22,3,FALSE()) -> Dorm Essentials | E22: =SUMIF('Sales Log'!$C$5:$C$111,INDEX($P$12:$P$29,MATCH(F22,$Q$12:$Q$29,0)),'Sales Log'!$F$5:$F$111) -> 87 | F22: =LARGE($Q$12:$Q$29,1) -> 10353 | P22: CS-2011 | Q22: =SUMIF('Sales Log'!$C$5:$C$111,P22,'Sales Log'!$H$5:$H$111) -> 314.3
B23: 2 | C23: =VLOOKUP(INDEX($P$12:$P$29,MATCH(F23,$Q$12:$Q$29,0)),Inventory!$A$5:$D$22,2,FALSE()) -> Organic Chemistry Manual | D23: =VLOOKUP(INDEX($P$12:$P$29,MATCH(F23,$Q$12:$Q$29,0)),Inventory!$A$5:$D$22,3,FALSE()) -> Textbooks | E23: =SUMIF('Sales Log'!$C$5:$C$111,INDEX($P$12:$P$29,MATCH(F23,$Q$12:$Q$29,0)),'Sales Log'!$F$5:$F$111) -> 96 | F23: =LARGE($Q$12:$Q$29,2) -> 9216 | P23: CS-2012 | Q23: =SUMIF('Sales Log'!$C$5:$C$111,P23,'Sales Log'!$H$5:$H$111) -> 11.98
B24: 3 | C24: =VLOOKUP(INDEX($P$12:$P$29,MATCH(F24,$Q$12:$Q$29,0)),Inventory!$A$5:$D$22,2,FALSE()) -> Intro to Psychology (Textbook) | D24: =VLOOKUP(INDEX($P$12:$P$29,MATCH(F24,$Q$12:$Q$29,0)),Inventory!$A$5:$D$22,3,FALSE()) -> Textbooks | E24: =SUMIF('Sales Log'!$C$5:$C$111,INDEX($P$12:$P$29,MATCH(F24,$Q$12:$Q$29,0)),'Sales Log'!$F$5:$F$111) -> 51 | F24: =LARGE($Q$12:$Q$29,3) -> 4589.49 | P24: CS-2013 | Q24: =SUMIF('Sales Log'!$C$5:$C$111,P24,'Sales Log'!$H$5:$H$111) -> 1574.55
B25: 4 | C25: =VLOOKUP(INDEX($P$12:$P$29,MATCH(F25,$Q$12:$Q$29,0)),Inventory!$A$5:$D$22,2,FALSE()) -> Calculus II Course Pack | D25: =VLOOKUP(INDEX($P$12:$P$29,MATCH(F25,$Q$12:$Q$29,0)),Inventory!$A$5:$D$22,3,FALSE()) -> Textbooks | E25: =SUMIF('Sales Log'!$C$5:$C$111,INDEX($P$12:$P$29,MATCH(F25,$Q$12:$Q$29,0)),'Sales Log'!$F$5:$F$111) -> 50 | F25: =LARGE($Q$12:$Q$29,4) -> 3725 | P25: CS-2014 | Q25: =SUMIF('Sales Log'!$C$5:$C$111,P25,'Sales Log'!$H$5:$H$111) -> 769.65
B26: 5 | C26: =VLOOKUP(INDEX($P$12:$P$29,MATCH(F26,$Q$12:$Q$29,0)),Inventory!$A$5:$D$22,2,FALSE()) -> Campus Store T-Shirt | D26: =VLOOKUP(INDEX($P$12:$P$29,MATCH(F26,$Q$12:$Q$29,0)),Inventory!$A$5:$D$22,3,FALSE()) -> Apparel & Spirit Wear | E26: =SUMIF('Sales Log'!$C$5:$C$111,INDEX($P$12:$P$29,MATCH(F26,$Q$12:$Q$29,0)),'Sales Log'!$F$5:$F$111) -> 138 | F26: =LARGE($Q$12:$Q$29,5) -> 2758.62 | P26: CS-2015 | Q26: =SUMIF('Sales Log'!$C$5:$C$111,P26,'Sales Log'!$H$5:$H$111) -> 10353
P27: CS-2016 | Q27: =SUMIF('Sales Log'!$C$5:$C$111,P27,'Sales Log'!$H$5:$H$111) -> 669.33
B28: Note: Top-5 ranking is fully formula-driven (SUMIF + LARGE + INDEX/MATCH) and recalculates automatically as Sales Log data changes. | P28: CS-2017 | Q28: =SUMIF('Sales Log'!$C$5:$C$111,P28,'Sales Log'!$H$5:$H$111) -> 408.87
P29: CS-2018 | Q29: =SUMIF('Sales Log'!$C$5:$C$111,P29,'Sales Log'!$H$5:$H$111) -> 334.89

Sheet Inventory
A1: CRESTWOOD UNIVERSITY CAMPUS STORE
A2: Inventory Register | Academic Year 2025 - 2026
A4: Product ID | B4: Product Name | C4: Category | D4: Unit Price | E4: Stock Qty | F4: Reorder Level | G4: Stock Value | H4: Status | I4: Last Updated
A5: CS-2001 | B5: Intro to Psychology (Textbook) | C5: Textbooks | D5: 89.99 | E5: 115 | F5: 40 | G5: =D5*E5 -> 10348.85 | H5: =IF(E5<=F5,"REORDER","OK") -> OK | I5: 46187
A6: CS-2002 | B6: Calculus II Course Pack | C6: Textbooks | D6: 74.5 | E6: 115 | F6: 40 | G6: =D6*E6 -> 8567.5 | H6: =IF(E6<=F6,"REORDER","OK") -> OK | I6: 46183
A7: CS-2003 | B7: Organic Chemistry Manual | C7: Textbooks | D7: 96 | E7: 48 | F7: 20 | G7: =D7*E7 -> 4608 | H7: =IF(E7<=F7,"REORDER","OK") -> OK | I7: 46185
A8: CS-2004 | B8: Crestwood Hoodie | C8: Apparel & Spirit Wear | D8: 44.99 | E8: 121 | F8: 40 | G8: =D8*E8 -> 5443.79 | H8: =IF(E8<=F8,"REORDER","OK") -> OK | I8: 46196
A9: CS-2005 | B9: Campus Store T-Shirt | C9: Apparel & Spirit Wear | D9: 19.99 | E9: 24 | F9: 30 | G9: =D9*E9 -> 479.76 | H9: =IF(E9<=F9,"REORDER","OK") -> REORDER | I9: 46192
A10: CS-2006 | B10: Varsity Cap | C10: Apparel & Spirit Wear | D10: 22.5 | E10: 36 | F10: 15 | G10: =D10*E10 -> 810 | H10: =IF(E10<=F10,"REORDER","OK") -> OK | I10: 46184
A11: CS-2007 | B11: Scientific Calculator | C11: Electronics & Supplies | D11: 24.99 | E11: 10 | F11: 40 | G11: =D11*E11 -> 249.9 | H11: =IF(E11<=F11,"REORDER","OK") -> REORDER | I11: 46189
A12: CS-2008 | B12: USB-C Charging Cable | C12: Electronics & Supplies | D12: 14.99 | E12: 115 | F12: 40 | G12: =D12*E12 -> 1723.85 | H12: =IF(E12<=F12,"REORDER","OK") -> OK | I12: 46181
A13: CS-2009 | B13: Wireless Mouse | C13: Electronics & Supplies | D13: 18.49 | E13: 40 | F13: 40 | G13: =D13*E13 -> 739.6 | H13: =IF(E13<=F13,"REORDER","OK") -> REORDER | I13: 46201
A14: CS-2010 | B14: Energy Drink 4pk | C14: Dining & Snacks | D14: 7.99 | E14: 135 | F14: 15 | G14: =D14*E14 -> 1078.65 | H14: =IF(E14<=F14,"REORDER","OK") -> OK | I14: 46200
A15: CS-2011 | B15: Trail Mix Bag | C15: Dining & Snacks | D15: 4.49 | E15: 9 | F15: 20 | G15: =D15*E15 -> 40.41 | H15: =IF(E15<=F15,"REORDER","OK") -> REORDER | I15: 46194
A16: CS-2012 | B16: Instant Ramen 6pk | C16: Dining & Snacks | D16: 5.99 | E16: 7 | F16: 30 | G16: =D16*E16 -> 41.93 | H16: =IF(E16<=F16,"REORDER","OK") -> REORDER | I16: 46191
... A22: CS-2018 | B22: Highlighter Pack | C22: School Supplies | D22: 5.49 | E22: 21 | F22: 25 | G22: =D22*E22 -> 115.29 | H22: =IF(E22<=F22,"REORDER","OK") -> REORDER | I22: 46191
A24: Summary
A25: Total SKUs | B25: =COUNTA(A5:A22) -> 18
A26: Total Stock Value | B26: =SUM(G5:G22) -> 50664.67
A27: Items Needing Reorder | B27: =COUNTIF(H5:H22,"REORDER") -> 7

Sheet Sales Log
A1: CRESTWOOD UNIVERSITY CAMPUS STORE
A2: Point-of-Sale Transaction Log | Spring Semester 2026
A4: Date | B4: Month | C4: Product ID | D4: Product Name | E4: Category | F4: Qty Sold | G4: Unit Price | H4: Revenue | I4: Payment Method
A5: 46039 | B5: =TEXT(A5,"mmm") -> Jan | C5: CS-2008 | D5: =VLOOKUP(C5,Inventory!$A$5:$D$22,2,FALSE()) -> USB-C Charging Cable | E5: =VLOOKUP(C5,Inventory!$A$5:$D$22,3,FALSE()) -> Electronics & Supplies | F5: 10 | G5: =VLOOKUP(C5,Inventory!$A$5:$D$22,4,FALSE()) -> 14.99 | H5: =F5*G5 -> 149.9 | I5: Student ID Card
A6: 46041 | B6: =TEXT(A6,"mmm") -> Jan | C6: CS-2003 | D6: =VLOOKUP(C6,Inventory!$A$5:$D$22,2,FALSE()) -> Organic Chemistry Manual | E6: =VLOOKUP(C6,Inventory!$A$5:$D$22,3,FALSE()) -> Textbooks | F6: 4 | G6: =VLOOKUP(C6,Inventory!$A$5:$D$22,4,FALSE()) -> 96 | H6: =F6*G6 -> 384 | I6: Mobile Pay
A7: 46050 | B7: =TEXT(A7,"mmm") -> Jan | C7: CS-2004 | D7: =VLOOKUP(C7,Inventory!$A$5:$D$22,2,FALSE()) -> Crestwood Hoodie | E7: =VLOOKUP(C7,Inventory!$A$5:$D$22,3,FALSE()) -> Apparel & Spirit Wear | F7: 10 | G7: =VLOOKUP(C7,Inventory!$A$5:$D$22,4,FALSE()) -> 44.99 | H7: =F7*G7 -> 449.9 | I7: Mobile Pay
A8: 46023 | B8: =TEXT(A8,"mmm") -> Jan | C8: CS-2003 | D8: =VLOOKUP(C8,Inventory!$A$5:$D$22,2,FALSE()) -> Organic Chemistry Manual | E8: =VLOOKUP(C8,Inventory!$A$5:$D$22,3,FALSE()) -> Textbooks | F8: 1 | G8: =VLOOKUP(C8,Inventory!$A$5:$D$22,4,FALSE()) -> 96 | H8: =F8*G8 -> 96 | I8: Credit Card
A9: 46024 | B9: =TEXT(A9,"mmm") -> Jan | C9: CS-2007 | D9: =VLOOKUP(C9,Inventory!$A$5:$D$22,2,FALSE()) -> Scientific Calculator | E9: =VLOOKUP(C9,Inventory!$A$5:$D$22,3,FALSE()) -> Electronics & Supplies | F9: 16 | G9: =VLOOKUP(C9,Inventory!$A$5:$D$22,4,FALSE()) -> 24.99 | H9: =F9*G9 -> 399.84 | I9: Mobile Pay
A10: 46036 | B10: =TEXT(A10,"mmm") -> Jan | C10: CS-2013 | D10: =VLOOKUP(C10,Inventory!$A$5:$D$22,2,FALSE()) -> Twin XL Bedsheet Set | E10: =VLOOKUP(C10,Inventory!$A$5:$D$22,3,FALSE()) -> Dorm Essentials | F10: 3 | G10: =VLOOKUP(C10,Inventory!$A$5:$D$22,4,FALSE()) -> 34.99 | H10: =F10*G10 -> 104.97 | I10: Credit Card
A11: 46033 | B11: =TEXT(A11,"mmm") -> Jan | C11: CS-2009 | D11: =VLOOKUP(C11,Inventory!$A$5:$D$22,2,FALSE()) -> Wireless Mouse | E11: =VLOOKUP(C11,Inventory!$A$5:$D$22,3,FALSE()) -> Electronics & Supplies | F11: 3 | G11: =VLOOKUP(C11,Inventory!$A$5:$D$22,4,FALSE()) -> 18.49 | H11: =F11*G11 -> 55.47 | I11: Cash
A12: 46023 | B12: =TEXT(A12,"mmm") -> Jan | C12: CS-2011 | D12: =VLOOKUP(C12,Inventory!$A$5:$D$22,2,FALSE()) -> Trail Mix Bag | E12: =VLOOKUP(C12,Inventory!$A$5:$D$22,3,FALSE()) -> Dining & Snacks | F12: 14 | G12: =VLOOKUP(C12,Inventory!$A$5:$D$22,4,FALSE()) -> 4.49 | H12: =F12*G12 -> 62.86 | I12: Student ID Card
A13: 46030 | B13: =TEXT(A13,"mmm") -> Jan | C13: CS-2005 | D13: =VLOOKUP(C13,Inventory!$A$5:$D$22,2,FALSE()) -> Campus Store T-Shirt | E13: =VLOOKUP(C13,Inventory!$A$5:$D$22,3,FALSE()) -> Apparel & Spirit Wear | F13: 4 | G13: =VLOOKUP(C13,Inventory!$A$5:$D$22,4,FALSE()) -> 19.99 | H13: =F13*G13 -> 79.96 | I13: Student ID Card
A14: 46037 | B14: =TEXT(A14,"mmm") -> Jan | C14: CS-2002 | D14: =VLOOKUP(C14,Inventory!$A$5:$D$22,2,FALSE()) -> Calculus II Course Pack | E14: =VLOOKUP(C14,Inventory!$A$5:$D$22,3,FALSE()) -> Textbooks | F14: 16 | G14: =VLOOKUP(C14,Inventory!$A$5:$D$22,4,FALSE()) -> 74.5 | H14: =F14*G14 -> 1192 | I14: Credit Card
A15: 46029 | B15: =TEXT(A15,"mmm") -> Jan | C15: CS-2018 | D15: =VLOOKUP(C15,Inventory!$A$5:$D$22,2,FALSE()) -> Highlighter Pack | E15: =VLOOKUP(C15,Inventory!$A$5:$D$22,3,FALSE()) -> School Supplies | F15: 15 | G15: =VLOOKUP(C15,Inventory!$A$5:$D$22,4,FALSE()) -> 5.49 | H15: =F15*G15 -> 82.35 | I15: Credit Card
A16: 46036 | B16: =TEXT(A16,"mmm") -> Jan | C16: CS-2005 | D16: =VLOOKUP(C16,Inventory!$A$5:$D$22,2,FALSE()) -> Campus Store T-Shirt | E16: =VLOOKUP(C16,Inventory!$A$5:$D$22,3,FALSE()) -> Apparel & Spirit Wear | F16: 13 | G16: =VLOOKUP(C16,Inventory!$A$5:$D$22,4,FALSE()) -> 19.99 | H16: =F16*G16 -> 259.87 | I16: Student ID Card
... A111: 46193 | B111: =TEXT(A111,"mmm") -> Jun | C111: CS-2017 | D111: =VLOOKUP(C111,Inventory!$A$5:$D$22,2,FALSE()) -> Mechanical Pencil Set | E111: =VLOOKUP(C111,Inventory!$A$5:$D$22,3,FALSE()) -> School Supplies | F111: 9 | G111: =VLOOKUP(C111,Inventory!$A$5:$D$22,4,FALSE()) -> 6.49 | H111: =F111*G111 -> 58.41 | I111: Credit Card
